askpablos_scrapy_api/__init__.py
askpablos_scrapy_api/auth.py
askpablos_scrapy_api/config.py
askpablos_scrapy_api/exceptions.py
askpablos_scrapy_api/middleware.py
askpablos_scrapy_api/operations.py
askpablos_scrapy_api/utils.py
askpablos_scrapy_api-0.4.8.dist-info/METADATA
askpablos_scrapy_api-0.4.8.dist-info/WHEEL
askpablos_scrapy_api-0.4.8.dist-info/licenses/LICENSE
askpablos_scrapy_api-0.4.8.dist-info/RECORD
