Metadata-Version: 2.4
Name: askpablos-scrapy-api
Version: 0.4.8
Summary: A professional Scrapy integration for seamlessly routing requests through AskPablos Proxy API with support for headless browser rendering and rotating IP addresses
Project-URL: source, https://github.com/fawadss1/askpablos_scrapy_api
Project-URL: Documentation, https://askpablos-scrapy-api.readthedocs.io/en/latest/index.html
Project-URL: Bug Tracker, https://github.com/fawadss1/askpablos_scrapy_api/issues
Author-email: Fawad Ali <fawadstar6@gmail.com>
License: MIT
License-File: LICENSE
Keywords: headless-browser,middleware,proxy,rotating-proxies,scrapy,web-scraping
Classifier: Development Status :: 4 - Beta
Classifier: Intended Audience :: Developers
Classifier: License :: OSI Approved :: MIT License
Classifier: Natural Language :: English
Classifier: Operating System :: OS Independent
Classifier: Programming Language :: Python
Classifier: Programming Language :: Python :: 3
Classifier: Programming Language :: Python :: 3.9
Classifier: Programming Language :: Python :: 3.10
Classifier: Programming Language :: Python :: 3.11
Classifier: Programming Language :: Python :: 3.12
Classifier: Programming Language :: Python :: 3.13
Classifier: Topic :: Internet :: WWW/HTTP
Classifier: Topic :: Software Development :: Libraries :: Python Modules
Requires-Python: >=3.9
Requires-Dist: requests>=2.25.0
Requires-Dist: scrapy>=2.6.0
